advanced_value_counts/__init__.py
advanced_value_counts/avc.py
advanced_value_counts/df_mutations.py
advanced_value_counts/value_checks.py
advanced_value_counts-1.0.0.dist-info/LICENSE
advanced_value_counts-1.0.0.dist-info/METADATA
advanced_value_counts-1.0.0.dist-info/WHEEL
advanced_value_counts-1.0.0.dist-info/top_level.txt
advanced_value_counts-1.0.0.dist-info/RECORD
