Metadata-Version: 2.1
Name: advanced-value-counts
Version: 1.0.0
Summary: A package to perform an advanced version of pandas' value_counts()
Author-email: Tomer Gabay <tomergabay001@gmail.com>
License: MIT
Project-URL: Homepage, https://github.com/sTomerG/advanced-value-counts
Project-URL: Bug Tracker, https://github.com/sTomerG/advanced-value-counts/issues
Keywords: eda,pandas,value_counts,groupby,advanced,counts,ratios,data science,data analytics
Classifier: Programming Language :: Python :: 3.8
Classifier: Programming Language :: Python :: 3.9
Classifier: Programming Language :: Python :: 3.10
Classifier: Programming Language :: Python :: Implementation :: CPython
Classifier: Programming Language :: Python :: Implementation :: PyPy
Classifier: License :: OSI Approved :: MIT License
Classifier: Operating System :: OS Independent
Classifier: Topic :: Scientific/Engineering
Requires-Python: >=3.8
License-File: LICENSE
Requires-Dist: pandas (<2,>=1.0.5)
Requires-Dist: numpy (<2,>=1.18.5)
Requires-Dist: seaborn (<1,>=0.9)
Provides-Extra: test
Requires-Dist: pytest (<8,>=7.1.2) ; extra == 'test'
Requires-Dist: flake8 (<6,>=5.0.4) ; extra == 'test'
Requires-Dist: tox (<4,>=3.25.1) ; extra == 'test'
